embeddings/__init__.py
embeddings/concat.py
embeddings/elmo.py
embeddings/embedding.py
embeddings/fasttext.py
embeddings/glove.py
embeddings/kazuma.py
test/__init__.py
test/speed_test.py
test/test_embeddings.py
embeddings-0.0.8.dist-info/LICENSE
embeddings-0.0.8.dist-info/METADATA
embeddings-0.0.8.dist-info/WHEEL
embeddings-0.0.8.dist-info/top_level.txt
embeddings-0.0.8.dist-info/RECORD
