Metadata-Version: 2.1
Name: embeddings
Version: 0.0.8
Summary: Pretrained word embeddings in Python.
Home-page: https://github.com/vzhong/embeddings
Author: Victor Zhong
Author-email: victor@victorzhong.com
License: MIT
Keywords: text nlp machine-learning
Platform: UNKNOWN
Classifier: Development Status :: 3 - Alpha
Classifier: Intended Audience :: Developers
Classifier: License :: OSI Approved :: MIT License
Classifier: Programming Language :: Python :: 3.5
Provides-Extra: dev
Provides-Extra: test
